APToolBox/DataFrameWrapper.cpython-310-x86_64-linux-gnu.so
APToolBox/InterpolateWrapper.cpython-310-x86_64-linux-gnu.so
APToolBox/__init__.py
APToolBox/ToolBox/__init__.py
APToolBox-1.1.0.dist-info/METADATA
APToolBox-1.1.0.dist-info/WHEEL
APToolBox-1.1.0.dist-info/top_level.txt
APToolBox-1.1.0.dist-info/RECORD
