Metadata-Version: 2.2
Name: APToolBox
Version: 1.1.0
Summary: A scientific computing toolbox
Home-page: https://example.com
Author: billogiovanni, tommasopiscitelli
Author-email: billogiova@gmail.com,  s309639@ds.units.it
Classifier: Programming Language :: Python :: 3
Classifier: License :: OSI Approved :: MIT License
Classifier: Operating System :: POSIX :: Linux
Requires-Python: >=3.6
